cli_print/__init__.py
cli_print/cli_print.py
cli_print-3.5.1.dist-info/LICENSE
cli_print-3.5.1.dist-info/METADATA
cli_print-3.5.1.dist-info/WHEEL
cli_print-3.5.1.dist-info/top_level.txt
cli_print-3.5.1.dist-info/RECORD
