Metadata-Version: 2.1
Name: cli-print
Version: 3.5.1
Summary: Colored CLI Print
Home-page: https://github.com/VisionNetworkProject/python-cli-print
Author: Vision Network
Author-email: michael@vision.network
License: UNKNOWN
Keywords: Colored,CLI,Terminal,Print
Platform: UNKNOWN
Classifier: Programming Language :: Python :: 3
Classifier: License :: OSI Approved :: MIT License
Classifier: Operating System :: OS Independent
Requires-Dist: colorama
